jupyterlab_deck/__init__.py
jupyterlab_deck/_version.py
jupyterlab_deck/tests/__init__.py
jupyterlab_deck/tests/test_metadata.py
jupyterlab_deck-0.2.0.data/data/share/jupyter/labextensions/@deathbeds/jupyterlab-deck/package.json
jupyterlab_deck-0.2.0.data/data/share/jupyter/labextensions/@deathbeds/jupyterlab-deck/schemas/@deathbeds/jupyterlab-deck/package.json.orig
jupyterlab_deck-0.2.0.data/data/share/jupyter/labextensions/@deathbeds/jupyterlab-deck/schemas/@deathbeds/jupyterlab-deck/plugin.json
jupyterlab_deck-0.2.0.data/data/share/jupyter/labextensions/@deathbeds/jupyterlab-deck/static/154.4a7913c09e75fc60c1f1.js
jupyterlab_deck-0.2.0.data/data/share/jupyter/labextensions/@deathbeds/jupyterlab-deck/static/154.4a7913c09e75fc60c1f1.js.map
jupyterlab_deck-0.2.0.data/data/share/jupyter/labextensions/@deathbeds/jupyterlab-deck/static/176.14a086d68b2525bcd250.js
jupyterlab_deck-0.2.0.data/data/share/jupyter/labextensions/@deathbeds/jupyterlab-deck/static/176.14a086d68b2525bcd250.js.map
jupyterlab_deck-0.2.0.data/data/share/jupyter/labextensions/@deathbeds/jupyterlab-deck/static/222.3b93934d4eaeabb96283.js
jupyterlab_deck-0.2.0.data/data/share/jupyter/labextensions/@deathbeds/jupyterlab-deck/static/222.3b93934d4eaeabb96283.js.map
jupyterlab_deck-0.2.0.data/data/share/jupyter/labextensions/@deathbeds/jupyterlab-deck/static/506.f90dc1516f0a4cb868e3.js
jupyterlab_deck-0.2.0.data/data/share/jupyter/labextensions/@deathbeds/jupyterlab-deck/static/506.f90dc1516f0a4cb868e3.js.map
jupyterlab_deck-0.2.0.data/data/share/jupyter/labextensions/@deathbeds/jupyterlab-deck/static/568.2f814165422050e9df90.js
jupyterlab_deck-0.2.0.data/data/share/jupyter/labextensions/@deathbeds/jupyterlab-deck/static/568.2f814165422050e9df90.js.map
jupyterlab_deck-0.2.0.data/data/share/jupyter/labextensions/@deathbeds/jupyterlab-deck/static/82.fcc5489b97181d5cdeb5.js
jupyterlab_deck-0.2.0.data/data/share/jupyter/labextensions/@deathbeds/jupyterlab-deck/static/82.fcc5489b97181d5cdeb5.js.map
jupyterlab_deck-0.2.0.dist-info/LICENSE
jupyterlab_deck-0.2.0.dist-info/WHEEL
jupyterlab_deck-0.2.0.dist-info/METADATA
jupyterlab_deck-0.2.0.dist-info/RECORD
