Metadata-Version: 2.1
Name: jupyterlab-deck
Version: 0.2.0
Summary: A lightweight presentation mode for JupyterLab.
Author-email: jupyterlab-deck contributors <deathbeds@googlegroups.com>
Requires-Python: >=3.8
Classifier: Framework :: Jupyter :: JupyterLab :: 3
Classifier: Framework :: Jupyter :: JupyterLab :: 4
Classifier: Framework :: Jupyter :: JupyterLab :: Extensions :: Prebuilt
Classifier: Framework :: Jupyter :: JupyterLab :: Extensions
Classifier: Framework :: Jupyter :: JupyterLab
Classifier: Framework :: Jupyter
Classifier: License :: OSI Approved :: BSD License
Classifier: Programming Language :: Python :: 3 :: Only
Classifier: Programming Language :: Python :: 3
Requires-Dist: jupyterlab >=3.5,<5.0.0a0
Requires-Dist: jupyterlab-fonts >=3.0.0
Project-URL: Bug Tracker, https://github.com/deathbeds/jupyterlab-deck/issues
Project-URL: Changelog, https://github.com/deathbeds/jupyterlab-deck/blob/main/CHANGELOG.md
Project-URL: Documentation, https://jupyterlab-deck.rtfd.io
Project-URL: Source, https://github.com/deathbeds/jupyterlab-deck
